setup.py
ID_distributions/Binomialdistribution.py
ID_distributions/Gaussiandistribution.py
ID_distributions/Generaldistribution.py
ID_distributions/__init__.py
ID_distributions.egg-info/PKG-INFO
ID_distributions.egg-info/SOURCES.txt
ID_distributions.egg-info/dependency_links.txt
ID_distributions.egg-info/not-zip-safe
ID_distributions.egg-info/top_level.txt